python_ack/__init__.py
python_ack/__main__.py
python_ack/__version__.py
python_ack/ack.py
python_ack-0.0.2.dist-info/LICENSE
python_ack-0.0.2.dist-info/METADATA
python_ack-0.0.2.dist-info/WHEEL
python_ack-0.0.2.dist-info/entry_points.txt
python_ack-0.0.2.dist-info/top_level.txt
python_ack-0.0.2.dist-info/RECORD
