Metadata-Version: 2.1
Name: python-ack
Version: 0.0.2
Summary: Python-ACK is a code-searching tool, similar to grep but optimized for programmers searching large trees of source code.
Home-page: https://github.com/klich3/python-ack
Author: Anton Sychev
Author-email: Anton Sychev <anton@sychev.xyz>
License: The MIT License (MIT)
Project-URL: Homepage, https://github.com/klich3/python-ack
Project-URL: Issues, https://github.com/klich3/python-ack/issues
Keywords: regexp,file,document,search
Classifier: Programming Language :: Python :: 3
Classifier: License :: OSI Approved :: MIT License
Classifier: Topic :: Software Development :: Libraries :: Python Modules
Requires-Python: >=3.8
License-File: LICENSE
Provides-Extra: build
Requires-Dist: build ; extra == 'build'
Requires-Dist: twine ; extra == 'build'
